{
  "name": "spider-vision",
  "version": "1.0.8",
  "description": "组件库",
  "main": "index.js",
  "scripts": {
    "test": "echo \"Error: no test specified\" && exit 1"
  },
  "dependencies": {
    "xstate": "^4.30.3",
    "@mui/icons-material": "^5.4.4",
    "@mui/material": "^5.4.4",
    "@emotion/react": "^11.8.1",
    "@emotion/styled": "^11.8.1",
    "react-router-dom": "^6.2.2",
    "@xstate/react": "^2.0.1",
    "spider-utils": "^1.0.14",
    "moment": "^2.29.1",
    "formik": "^2.2.9",
    "@mui/styles": "^5.4.4",
    "@mui/lab": "^5.0.0-alpha.71"
  },
  "keywords": [
    "react"
  ],
  "author": "visionary",
  "license": "ISC"
}
